{
  "status": "YELLOW",
  "score": 51,
  "label": "NEUTRAL",
  "reasons": [
    "日経225 -0.10%",
    "TOPIX +0.67%"
  ],
  "sectors": [
    {
      "name": "닛케이225",
      "signal": "bearish",
      "change_pct": -0.09,
      "score": 49
    },
    {
      "name": "TOPIX",
      "signal": "bullish",
      "change_pct": 0.67,
      "score": 53
    },
    {
      "name": "식품",
      "signal": "bullish",
      "change_pct": 1.37,
      "score": 56
    },
    {
      "name": "에너지",
      "signal": "bullish",
      "change_pct": 1.38,
      "score": 56
    },
    {
      "name": "건설",
      "signal": "bearish",
      "change_pct": -0.09,
      "score": 49
    },
    {
      "name": "소재",
      "signal": "bullish",
      "change_pct": 1.59,
      "score": 57
    },
    {
      "name": "의료",
      "signal": "bullish",
      "change_pct": 1.62,
      "score": 58
    },
    {
      "name": "은행",
      "signal": "bullish",
      "change_pct": 0.51,
      "score": 52
    },
    {
      "name": "운송",
      "signal": "bullish",
      "change_pct": 0.87,
      "score": 54
    },
    {
      "name": "전자",
      "signal": "bullish",
      "change_pct": 2.41,
      "score": 62
    }
  ],
  "metrics": {},
  "nikkei_close": 53322.85,
  "nikkei_change_pct": -0.1,
  "topix_close": 2620.8,
  "topix_change_pct": 0.67,
  "updated_at": "2026-02-01T15:18:42.084430"
}